neural_lowthrust/__init__.py
neural_lowthrust/models/eigen_model_large/layer0_bias.csv
neural_lowthrust/models/eigen_model_large/layer0_weight.csv
neural_lowthrust/models/eigen_model_large/layer1_bias.csv
neural_lowthrust/models/eigen_model_large/layer1_weight.csv
neural_lowthrust/models/eigen_model_large/layer2_bias.csv
neural_lowthrust/models/eigen_model_large/layer2_weight.csv
neural_lowthrust/models/eigen_model_large/layer3_bias.csv
neural_lowthrust/models/eigen_model_large/layer3_weight.csv
neural_lowthrust/models/eigen_model_large/layer4_bias.csv
neural_lowthrust/models/eigen_model_large/layer4_weight.csv
neural_lowthrust/models/eigen_model_large/layer5_bias.csv
neural_lowthrust/models/eigen_model_large/layer5_weight.csv
neural_lowthrust/models/eigen_model_large/layer6_bias.csv
neural_lowthrust/models/eigen_model_large/layer6_weight.csv
neural_lowthrust/models/eigen_model_large/layer7_bias.csv
neural_lowthrust/models/eigen_model_large/layer7_weight.csv
neural_lowthrust/models/eigen_model_large/layer8_bias.csv
neural_lowthrust/models/eigen_model_large/layer8_weight.csv
neural_lowthrust/models/eigen_model_large/layer9_bias.csv
neural_lowthrust/models/eigen_model_large/layer9_weight.csv
neural_lowthrust/models/eigen_model_large/X_mean.csv
neural_lowthrust/models/eigen_model_large/X_scale.csv
neural_lowthrust/models/eigen_model_large/Y_mean.csv
neural_lowthrust/models/eigen_model_large/Y_scale.csv
neural_lowthrust/models/eigen_model_tmin_large/layer0_bias.csv
neural_lowthrust/models/eigen_model_tmin_large/layer0_weight.csv
neural_lowthrust/models/eigen_model_tmin_large/layer1_bias.csv
neural_lowthrust/models/eigen_model_tmin_large/layer1_weight.csv
neural_lowthrust/models/eigen_model_tmin_large/layer2_bias.csv
neural_lowthrust/models/eigen_model_tmin_large/layer2_weight.csv
neural_lowthrust/models/eigen_model_tmin_large/layer3_bias.csv
neural_lowthrust/models/eigen_model_tmin_large/layer3_weight.csv
neural_lowthrust/models/eigen_model_tmin_large/layer4_bias.csv
neural_lowthrust-0.1.2.dist-info/METADATA
neural_lowthrust-0.1.2.dist-info/WHEEL
neural_lowthrust-0.1.2.dist-info/licenses/LICENSE
neural_lowthrust-0.1.2.dist-info/RECORD
