Metadata-Version: 2.2
Name: neural_lowthrust
Version: 0.1.2
Summary: Eigen-based low-thrust trajectory predictor
Author-Email: Zhong Zhang <zhongzhang.astro@gmail.com>
Classifier: License :: OSI Approved :: Mozilla Public License 2.0 (MPL 2.0)
Requires-Python: >=3.9
Requires-Dist: numpy
